odoo/addons/product_total_weight_from_packaging/README.rst
odoo/addons/product_total_weight_from_packaging/__init__.py
odoo/addons/product_total_weight_from_packaging/__manifest__.py
odoo/addons/product_total_weight_from_packaging/i18n/es.po
odoo/addons/product_total_weight_from_packaging/i18n/product_total_weight_from_packaging.pot
odoo/addons/product_total_weight_from_packaging/models/__init__.py
odoo/addons/product_total_weight_from_packaging/models/product.py
odoo/addons/product_total_weight_from_packaging/readme/CONTRIBUTORS.rst
odoo/addons/product_total_weight_from_packaging/readme/DESCRIPTION.rst
odoo/addons/product_total_weight_from_packaging/static/description/icon.png
odoo/addons/product_total_weight_from_packaging/static/description/index.html
odoo/addons/product_total_weight_from_packaging/tests/__init__.py
odoo/addons/product_total_weight_from_packaging/tests/test_product_total_weight_from_packaging.py
odoo14_addon_product_total_weight_from_packaging-14.0.1.1.1.dist-info/METADATA
odoo14_addon_product_total_weight_from_packaging-14.0.1.1.1.dist-info/WHEEL
odoo14_addon_product_total_weight_from_packaging-14.0.1.1.1.dist-info/top_level.txt
odoo14_addon_product_total_weight_from_packaging-14.0.1.1.1.dist-info/RECORD
