Metadata-Version: 2.1
Name: odoo14-addon-product-total-weight-from-packaging
Version: 14.0.1.1.1
Summary: Compute estimated weight based on product's packaging weights
Home-page: https://github.com/OCA/product-attribute
Author: Camptocamp, Odoo Community Association (OCA)
Author-email: support@odoo-community.org
License: AGPL-3
Platform: UNKNOWN
Classifier: Programming Language :: Python
Classifier: Framework :: Odoo
Classifier: Framework :: Odoo :: 14.0
Classifier: License :: OSI Approved :: GNU Affero General Public License v3
Classifier: Development Status :: 4 - Beta
Requires-Python: >=3.6
Requires-Dist: odoo14-addon-product-packaging-dimension
Requires-Dist: odoo14-addon-stock-packaging-calculator
Requires-Dist: odoo (<14.1dev,>=14.0a)
